{
  "version": "4.5.13",
  "flags": {},
  "shapes": [
    {
      "label": "ground.parkingspace",
      "points": [
        [
          311.21495327102804,
          262.14953271028037
        ],
        [
          389.2523364485981,
          263.55140186915884
        ],
        [
          411.21495327102804,
          101.4018691588785
        ],
        [
          338.31775700934577,
          101.4018691588785
        ]
      ],
      "group_id": null,
      "shape_type": "polygon",
      "flags": {}
    },
    {
      "label": "ground.parkingspace",
      "points": [
        [
          457.0093457943925,
          96.26168224299064
        ],
        [
          439.7196261682243,
          264.95327102803736
        ],
        [
          530.8411214953271,
          265.42056074766356
        ],
        [
          538.7850467289719,
          93.9252336448598
        ]
      ],
      "group_id": null,
      "shape_type": "polygon",
      "flags": {}
    },
    {
      "label": "ground.parkingspace",
      "points": [
        [
          538.7850467289719,
          266.3551401869159
        ],
        [
          632.7102803738318,
          265.42056074766356
        ],
        [
          627.1028037383177,
          89.25233644859813
        ],
        [
          545.3271028037383,
          92.5233644859813
        ]
      ],
      "group_id": null,
      "shape_type": "polygon",
      "flags": {}
    },
    {
      "label": "ground.parkingspace",
      "points": [
        [
          645.3271028037383,
          265.42056074766356
        ],
        [
          739.7196261682243,
          267.2897196261682
        ],
        [
          741.1214953271027,
          87.38317757009345
        ],
        [
          657.0093457943925,
          88.31775700934578
        ]
      ],
      "group_id": null,
      "shape_type": "polygon",
      "flags": {}
    },
    {
      "label": "ground.parkingspace",
      "points": [
        [
          795.7943925233644,
          267.2897196261682
        ],
        [
          892.9906542056074,
          263.55140186915884
        ],
        [
          877.5700934579439,
          85.98130841121495
        ],
        [
          791.588785046729,
          87.85046728971962
        ],
        [
          792.0560747663551,
          173.83177570093457
        ]
      ],
      "group_id": null,
      "shape_type": "polygon",
      "flags": {}
    },
    {
      "label": "ground.parkingspace",
      "points": [
        [
          899.0654205607476,
          264.4859813084112
        ],
        [
          991.1214953271027,
          261.6822429906542
        ],
        [
          976.1682242990654,
          86.91588785046729
        ],
        [
          882.4074074074074,
          86.1111111111111
        ]
      ],
      "group_id": null,
      "shape_type": "polygon",
      "flags": {}
    },
    {
      "label": "ground.parkingspace",
      "points": [
        [
          995.7943925233644,
          260.74766355140184
        ],
        [
          983.644859813084,
          87.38317757009345
        ],
        [
          1062.6168224299065,
          87.38317757009345
        ],
        [
          1084.5794392523364,
          259.8130841121495
        ]
      ],
      "group_id": null,
      "shape_type": "polygon",
      "flags": {}
    },
    {
      "label": "ground.parkingspace",
      "points": [
        [
          437.4045801526717,
          455.34351145038164
        ],
        [
          519.8473282442748,
          454.1984732824427
        ],
        [
          514.5038167938931,
          646.1832061068702
        ],
        [
          435.87786259541986,
          643.8931297709923
        ]
      ],
      "group_id": null,
      "shape_type": "polygon",
      "flags": {}
    },
    {
      "label": "ground.parkingspace",
      "points": [
        [
          302.29007633587787,
          458.39694656488547
        ],
        [
          387.7862595419847,
          456.4885496183206
        ],
        [
          386.6412213740458,
          641.9847328244275
        ],
        [
          302.67175572519085,
          638.1679389312977
        ]
      ],
      "group_id": null,
      "shape_type": "polygon",
      "flags": {}
    },
    {
      "label": "ground.parkingspace",
      "points": [
        [
          216.793893129771,
          458.39694656488547
        ],
        [
          291.6030534351145,
          456.87022900763355
        ],
        [
          293.1297709923664,
          637.4045801526718
        ],
        [
          223.66412213740458,
          637.0229007633587
        ]
      ],
      "group_id": null,
      "shape_type": "polygon",
      "flags": {}
    },
    {
      "label": "traffic.lane.parkingspacesolidline",
      "points": [
        [
          429.1139240506329,
          448.1012658227848
        ],
        [
          461.2658227848101,
          447.8481012658228
        ],
        [
          461.2658227848101,
          454.6835443037975
        ],
        [
          437.46835443037975,
          455.44303797468353
        ],
        [
          435.44303797468353,
          643.7974683544304
        ],
        [
          514.6835443037975,
          646.5822784810126
        ],
        [
          520.253164556962,
          454.1772151898734
        ],
        [
          493.67088607594934,
          454.4303797468354
        ],
        [
          493.92405063291136,
          447.59493670886076
        ],
        [
          526.0759493670886,
          447.8481012658228
        ],
        [
          519.746835443038,
          651.1392405063291
        ],
        [
          429.1139240506329,
          649.1139240506329
        ]
      ],
      "group_id": null,
      "shape_type": "polygon",
      "flags": {}
    },
    {
      "label": "traffic.lane.parkingspacesolidline",
      "points": [
        [
          361.0126582278481,
          450.63291139240505
        ],
        [
          361.0126582278481,
          456.96202531645565
        ],
        [
          388.1012658227848,
          456.2025316455696
        ],
        [
          387.0886075949367,
          642.0253164556962
        ],
        [
          302.7848101265823,
          640.0
        ],
        [
          302.0253164556962,
          457.9746835443038
        ],
        [
          325.0632911392405,
          457.46835443037975
        ],
        [
          325.56962025316454,
          450.126582278481
        ],
        [
          270.63291139240505,
          451.1392405063291
        ],
        [
          270.63291139240505,
          457.46835443037975
        ],
        [
          291.6455696202531,
          456.70886075949363
        ],
        [
          293.92405063291136,
          637.7215189873417
        ],
        [
          223.2911392405063,
          637.4683544303797
        ],
        [
          216.70886075949366,
          457.9746835443038
        ],
        [
          233.67088607594937,
          457.9746835443038
        ],
        [
          234.1772151898734,
          452.1518987341772
        ],
        [
          208.86075949367088,
          452.65822784810126
        ],
        [
          214.68354430379745,
          643.5443037974683
        ],
        [
          300.0,
          644.8101265822785
        ],
        [
          394.1772151898734,
          648.1012658227847
        ],
        [
          393.4177215189873,
          450.126582278481
        ]
      ],
      "group_id": null,
      "shape_type": "polygon",
      "flags": {}
    },
    {
      "label": "traffic.lane.parkingspacesolidline",
      "points": [
        [
          365.6746031746032,
          263.2936507936508
        ],
        [
          365.27777777777777,
          269.44444444444446
        ],
        [
          394.8412698412698,
          269.64285714285717
        ],
        [
          417.26190476190476,
          97.22222222222223
        ],
        [
          334.3253968253968,
          96.62698412698413
        ],
        [
          303.968253968254,
          268.6507936507937
        ],
        [
          328.1746031746032,
          269.04761904761904
        ],
        [
          329.36507936507934,
          262.6984126984127
        ],
        [
          310.91269841269843,
          262.3015873015873
        ],
        [
          338.0952380952381,
          101.19047619047619
        ],
        [
          411.3095238095238,
          101.19047619047619
        ],
        [
          389.6825396825397,
          263.4920634920635
        ]
      ],
      "group_id": null,
      "shape_type": "polygon",
      "flags": {}
    },
    {
      "label": "traffic.lane.parkingspacesolidline",
      "points": [
        [
          439.5408163265306,
          265.3061224489796
        ],
        [
          462.2448979591837,
          265.05102040816325
        ],
        [
          461.4795918367347,
          271.1734693877551
        ],
        [
          431.88775510204084,
          270.9183673469388
        ],
        [
          450.51020408163265,
          91.07142857142857
        ],
        [
          631.1224489795918,
          83.92857142857143
        ],
        [
          707.9081632653061,
          81.88775510204081
        ],
        [
          746.9387755102041,
          81.63265306122449
        ],
        [
          746.4285714285714,
          272.7040816326531
        ],
        [
          714.2857142857143,
          271.9387755102041
        ],
        [
          714.2857142857143,
          266.5816326530612
        ],
        [
          740.0510204081633,
          267.3469387755102
        ],
        [
          741.0714285714286,
          86.73469387755102
        ],
        [
          656.8877551020408,
          87.75510204081633
        ],
        [
          645.1530612244898,
          265.5612244897959
        ],
        [
          670.4081632653061,
          266.3265306122449
        ],
        [
          669.6428571428571,
          271.9387755102041
        ],
        [
          608.4183673469388,
          272.1938775510204
        ],
        [
          608.1632653061224,
          265.81632653061223
        ],
        [
          633.1632653061224,
          265.5612244897959
        ],
        [
          627.295918367347,
          89.03061224489797
        ],
        [
          545.1530612244898,
          92.34693877551021
        ],
        [
          538.7755102040817,
          266.3265306122449
        ],
        [
          562.2448979591837,
          266.5816326530612
        ],
        [
          561.7346938775511,
          273.46938775510205
        ],
        [
          506.12244897959187,
          272.7040816326531
        ],
        [
          506.3775510204082,
          265.81632653061223
        ],
        [
          531.3775510204082,
          265.81632653061223
        ],
        [
          538.7755102040817,
          92.85714285714286
        ],
        [
          456.88775510204084,
          95.40816326530613
        ]
      ],
      "group_id": null,
      "shape_type": "polygon",
      "flags": {}
    },
    {
      "label": "traffic.lane.parkingspacesolidline",
      "points": [
        [
          821.7592592592592,
          266.66666666666663
        ],
        [
          821.7592592592592,
          271.52777777777777
        ],
        [
          789.3518518518518,
          272.22222222222223
        ],
        [
          786.8055555555555,
          83.10185185185185
        ],
        [
          1068.5185185185185,
          82.17592592592592
        ],
        [
          1094.4444444444443,
          266.2037037037037
        ],
        [
          1063.888888888889,
          266.43518518518516
        ],
        [
          1063.1944444444443,
          260.41666666666663
        ],
        [
          1084.9537037037037,
          260.18518518518516
        ],
        [
          1062.7314814814815,
          86.80555555555554
        ],
        [
          983.3333333333333,
          86.34259259259258
        ],
        [
          995.6018518518517,
          261.5740740740741
        ],
        [
          1024.537037037037,
          261.1111111111111
        ],
        [
          1024.537037037037,
          267.1296296296296
        ],
        [
          968.7499999999999,
          268.98148148148147
        ],
        [
          968.5185185185185,
          262.96296296296293
        ],
        [
          991.4351851851851,
          262.037037037037
        ],
        [
          976.1574074074074,
          86.34259259259258
        ],
        [
          882.1759259259259,
          85.64814814814814
        ],
        [
          898.8425925925925,
          264.35185185185185
        ],
        [
          926.3888888888888,
          263.6574074074074
        ],
        [
          926.3888888888888,
          270.13888888888886
        ],
        [
          868.0555555555555,
          270.60185185185185
        ],
        [
          867.824074074074,
          264.8148148148148
        ],
        [
          893.0555555555555,
          263.6574074074074
        ],
        [
          877.7777777777777,
          85.64814814814814
        ],
        [
          791.4351851851851,
          87.26851851851852
        ],
        [
          792.1296296296296,
          173.37962962962962
        ],
        [
          795.6018518518518,
          266.89814814814815
        ]
      ],
      "group_id": null,
      "shape_type": "polygon",
      "flags": {}
    },
    {
      "label": "static_object.construction.wall",
      "points": [
        [
          401.8711018711018,
          238.66943866943865
        ],
        [
          429.10602910602904,
          238.25363825363823
        ],
        [
          433.4719334719334,
          215.59251559251558
        ],
        [
          408.7318087318087,
          215.59251559251558
        ]
      ],
      "group_id": null,
      "shape_type": "polygon",
      "flags": {}
    },
    {
      "label": "static_object.construction.wall",
      "points": [
        [
          749.1304347826086,
          216.52173913043475
        ],
        [
          749.3478260869564,
          237.82608695652172
        ],
        [
          783.0434782608695,
          238.26086956521738
        ],
        [
          782.391304347826,
          216.52173913043475
        ]
      ],
      "group_id": null,
      "shape_type": "polygon",
      "flags": {}
    },
    {
      "label": "static_object.construction.wall",
      "points": [
        [
          398.4782608695652,
          486.73913043478257
        ],
        [
          427.39130434782606,
          486.52173913043475
        ],
        [
          427.1739130434782,
          513.2608695652174
        ],
        [
          398.9130434782608,
          513.2608695652174
        ]
      ],
      "group_id": null,
      "shape_type": "polygon",
      "flags": {}
    },
    {
      "label": "static_object.construction.wall.occlusion",
      "points": [
        [
          427.39130434782606,
          513.4782608695651
        ],
        [
          136,
          719
        ],
        [
          0,
          719
        ],
        [
          0,
          690
        ],
        [
          398.5234899328859,
          486.4429530201342
        ],
        [
          398.79194630872485,
          513.2885906040268
        ]
      ],
      "group_id": null,
      "shape_type": "polygon",
      "flags": {}
    },
    {
      "label": "static_object.construction.wall.occlusion",
      "points": [
        [
          433.52803738317755,
          215.42056074766353
        ],
        [
          127,
          0
        ],
        [
          0,
          0
        ],
        [
          0,
          55
        ],
        [
          402.13675213675214,
          238.67521367521368
        ],
        [
          408.7606837606838,
          215.3846153846154
        ]
      ],
      "group_id": null,
      "shape_type": "polygon",
      "flags": {}
    },
    {
      "label": "static_object.construction.wall.occlusion",
      "points": [
        [
          748.9864864864865,
          216.21621621621622
        ],
        [
          910,
          0
        ],
        [
          1059,
          0
        ],
        [
          783.303730017762,
          238.89875666074602
        ],
        [
          782.7708703374778,
          215.98579040852576
        ]
      ],
      "group_id": null,
      "shape_type": "polygon",
      "flags": {}
    },
    {
      "label": "static_object.construction.wall",
      "points": [
        [
          444.758064516129,
          81.45161290322581
        ],
        [
          443.9516129032258,
          88.70967741935483
        ],
        [
          412.90322580645164,
          90.7258064516129
        ],
        [
          412.0967741935484,
          84.6774193548387
        ],
        [
          259.8765432098765,
          92.59259259259258
        ],
        [
          130,
          0
        ],
        [
          910,
          0
        ],
        [
          857.9881656804733,
          69.8224852071006
        ],
        [
          783.4319526627219,
          71.59763313609467
        ],
        [
          779.2899408284023,
          82.84023668639054
        ],
        [
          753.2544378698225,
          83.4319526627219
        ],
        [
          753.2544378698225,
          71.00591715976331
        ],
        [
          642.0118343195267,
          71.59763313609467
        ]
      ],
      "group_id": null,
      "shape_type": "polygon",
      "flags": {}
    },
    {
      "label": "static_object.construction.wall",
      "points": [
        [
          1092.2522522522522,
          210.63063063063063
        ],
        [
          1095.1351351351352,
          236.93693693693695
        ],
        [
          1118.2203389830509,
          238.135593220339
        ],
        [
          1114.8305084745764,
          211.4406779661017
        ]
      ],
      "group_id": null,
      "shape_type": "polygon",
      "flags": {}
    },
    {
      "label": "static_object.construction.wall",
      "points": [
        [
          979.5454545454545,
          68.18181818181819
        ],
        [
          1073.2954545454545,
          67.04545454545455
        ],
        [
          1077.2727272727273,
          80.68181818181819
        ],
        [
          1279,
          85
        ],
        [
          1279,
          0
        ],
        [
          1060,
          0
        ]
      ],
      "group_id": null,
      "shape_type": "polygon",
      "flags": {}
    },
    {
      "label": "static_object.construction.wall",
      "points": [
        [
          159.08247422680412,
          128.70103092783506
        ],
        [
          137.43298969072166,
          236.9484536082474
        ],
        [
          66.29896907216497,
          242.1030927835052
        ],
        [
          0,
          225
        ],
        [
          0,
          56
        ]
      ],
      "group_id": null,
      "shape_type": "polygon",
      "flags": {}
    },
    {
      "label": "static_object.construction.wall",
      "points": [
        [
          80.73195876288659,
          447.25773195876286
        ],
        [
          117.84536082474227,
          446.2268041237113
        ],
        [
          115.78350515463919,
          458.5979381443299
        ],
        [
          105.4742268041237,
          461.69072164948454
        ],
        [
          103.41237113402062,
          485.4020618556701
        ],
        [
          113.7216494845361,
          487.46391752577324
        ],
        [
          113.7216494845361,
          629.7319587628866
        ],
        [
          0,
          690
        ],
        [
          0,
          465
        ]
      ],
      "group_id": null,
      "shape_type": "polygon",
      "flags": {}
    },
    {
      "label": "static_object.construction.wall",
      "points": [
        [
          227.12371134020617,
          656.5360824742269
        ],
        [
          385.88659793814435,
          662.7216494845361
        ],
        [
          395.16494845360825,
          655.5051546391753
        ],
        [
          426.09278350515467,
          654.4742268041238
        ],
        [
          426.09278350515467,
          663.7525773195877
        ],
        [
          502.3814432989691,
          665.8144329896908
        ],
        [
          515.7835051546392,
          663.7525773195877
        ],
        [
          581.7628865979382,
          501.8969072164948
        ],
        [
          719.9072164948453,
          511.1752577319588
        ],
        [
          724.0309278350516,
          507.0515463917526
        ],
        [
          752.8969072164949,
          507.0515463917526
        ],
        [
          753.9278350515464,
          492.6185567010309
        ],
        [
          796.1958762886599,
          491.58762886597935
        ],
        [
          799.2886597938144,
          503.9587628865979
        ],
        [
          880.7319587628866,
          504.9896907216495
        ],
        [
          881.7628865979382,
          478.18556701030934
        ],
        [
          1011.659793814433,
          477.1546391752578
        ],
        [
          1110.6288659793815,
          513.2371134020618
        ],
        [
          1124.0309278350517,
          512.2061855670104
        ],
        [
          1123.0,
          498.80412371134025
        ],
        [
          1160.1134020618556,
          497.7731958762887
        ],
        [
          1194.1340206185566,
          518.3917525773196
        ],
        [
          1208.5670103092784,
          512.2061855670104
        ],
        [
          1279,
          531
        ],
        [
          1279,
          719
        ],
        [
          138,
          719
        ]
      ],
      "group_id": null,
      "shape_type": "polygon",
      "flags": {}
    },
    {
      "label": "static_object.construction.wall.occlusion",
      "points": [
        [
          1092.1908893709326,
          210.41214750542298
        ],
        [
          1279,
          144
        ],
        [
          1279,
          195
        ],
        [
          1118.2432432432431,
          238.28828828828827
        ],
        [
          1114.8648648648648,
          211.03603603603602
        ]
      ],
      "group_id": null,
      "shape_type": "polygon",
      "flags": {}
    },
    {
      "label": "traffic.lane.solidlineyellow",
      "points": [
        [
          638.423645320197,
          283.2512315270936
        ],
        [
          481.28078817733984,
          282.2660098522167
        ],
        [
          224.63054187192117,
          274.38423645320194
        ],
        [
          0,
          268
        ],
        [
          0,
          275
        ],
        [
          223.40425531914894,
          281.531914893617
        ],
        [
          480.5405405405405,
          289.72972972972974
        ],
        [
          638.9189189189188,
          290.5405405405405
        ],
        [
          718.6486486486486,
          289.72972972972974
        ],
        [
          905.9459459459459,
          286.7567567567567
        ],
        [
          1224.8648648648648,
          277.56756756756755
        ],
        [
          1279,
          278
        ],
        [
          1279,
          272
        ],
        [
          1183.1804281345567,
          273.39449541284404
        ],
        [
          908.5626911314985,
          279.20489296636083
        ],
        [
          783.1804281345566,
          282.56880733944956
        ]
      ],
      "group_id": null,
      "shape_type": "polygon",
      "flags": {}
    },
    {
      "label": "traffic.lane.solidlineyellow",
      "points": [
        [
          638.5496183206106,
          422.9007633587786
        ],
        [
          492.36641221374043,
          423.66412213740455
        ],
        [
          304.96183206106866,
          429.3893129770992
        ],
        [
          150.0,
          433.587786259542
        ],
        [
          0,
          440
        ],
        [
          0,
          445
        ],
        [
          150.46296296296296,
          437.96296296296293
        ],
        [
          327.3148148148148,
          432.8703703703703
        ],
        [
          544.9074074074074,
          430.09259259259255
        ],
        [
          687.037037037037,
          431.0185185185185
        ],
        [
          976.8518518518517,
          436.574074074074
        ],
        [
          1279,
          443
        ],
        [
          1279,
          438
        ],
        [
          977.0642201834862,
          431.1926605504587
        ],
        [
          688.3792048929664,
          424.15902140672785
        ]
      ],
      "group_id": null,
      "shape_type": "polygon",
      "flags": {}
    },
    {
      "label": "ground.road",
      "points": [
        [
          1225.0618556701031,
          279.21649484536084
        ],
        [
          1279,
          279
        ],
        [
          1279,
          436
        ],
        [
          977.3504273504274,
          430.7692307692308
        ],
        [
          688.4615384615385,
          423.0769230769231
        ],
        [
          638.8888888888889,
          421.7948717948718
        ],
        [
          492.7350427350428,
          423.50427350427356
        ],
        [
          305.12820512820514,
          428.63247863247864
        ],
        [
          150.42735042735043,
          432.9059829059829
        ],
        [
          0,
          439
        ],
        [
          0,
          274
        ],
        [
          223.2876712328767,
          281.5068493150685
        ],
        [
          480.81761006289304,
          289.62264150943395
        ],
        [
          639.622641509434,
          290.8805031446541
        ],
        [
          718.8679245283018,
          289.62264150943395
        ],
        [
          905.9748427672955,
          286.79245283018867
        ]
      ],
      "group_id": null,
      "shape_type": "polygon",
      "flags": {}
    }
  ],
  "imagePath": "..\\iamges\\743.png",
  "imageData": null,
  "imageHeight": 720,
  "imageWidth": 1280
}